CHANGELOG.md
LICENSE
MANIFEST.in
README.md
setup.cfg
setup.py
tox.ini
whatwg_url.py
tests/__init__.py
tests/test_special_cases.py
tests/test_url.py
tests/test_urllib.py
tests/test_web_platform_tests.py
tests/testdata.json
whatwg_url.egg-info/PKG-INFO
whatwg_url.egg-info/SOURCES.txt
whatwg_url.egg-info/dependency_links.txt
whatwg_url.egg-info/requires.txt
whatwg_url.egg-info/top_level.txt