Metadata-Version: 2.1
Name: whatwg-url
Version: 2018.8.26
Summary: Python implementation of the WHATWG URL Living Standard
Home-page: https://github.com/SethMichaelLarson/whatwg-url
Author: Seth Michael Larson
Author-email: sethmichaellarson@gmail.com
License: Apache-2.0
Platform: UNKNOWN
Classifier: Development Status :: 4 - Beta
Classifier: Intended Audience :: Developers
Classifier: Natural Language :: English
Classifier: License :: OSI Approved :: Apache Software License
Classifier: Programming Language :: Python :: 2
Classifier: Programming Language :: Python :: 2.7
Classifier: Programming Language :: Python :: 3
Classifier: Programming Language :: Python :: 3.4
Classifier: Programming Language :: Python :: 3.5
Classifier: Programming Language :: Python :: 3.6
Classifier: Programming Language :: Python :: 3.7
Classifier: Topic :: Internet
